<note>
	<name>数据质量版本发布说明20190418（V1.4.1）</name>
	<date>2019/04/18</date>
	<specialityList>
		<name>特性清单</name>
		<item>
			<Introduction>场景修复</Introduction>
			<content>周期全量采集资源质检结果不准确。</content>
			<sysName> 质检报告</sysName>
			<remark></remark>
		</item>	
		<item>
			<Introduction>功能优化</Introduction>
			<content>质检方案设计方案类型及时间操作逻辑优化，质检方案
功能优化 质检方案设计画布美化。</content>
			<sysName> 质检方案</sysName>
			<remark></remark>
		</item>	
		<item>
			<Introduction>功能优化</Introduction>
			<content>质检报告周期性报告折线图优化，质检监控增加报告周期字段。</content>
			<sysName> 质检报告</sysName>
			<remark></remark>
		</item>	
		<item>
			<Introduction>功能优化</Introduction>
			<content> 质检方案、质检报告高级搜索优化。</content>
			<sysName> 质检方案、质检报告</sysName>
			<remark></remark>
		</item>	
		<item>
			<Introduction>产品优化</Introduction>
			<content>统一UI样式，优化提示样式，优化页面排版。</content>
			<sysName>产品优化</sysName>
			<remark></remark>
		</item>			
	</specialityList>
	<changeList>
		<name>重大变更列表</name>
                    <item>
			<content>无</content>
		</item>          
	</changeList>
	<finishedPunchList>
		<name>解决问题清单</name>
		
	</finishedPunchList>
	<questionList>
		<name>已知问题和限制</name>	
    	<!-- <item>
			<content></content>
			<Influence></Influence>
			<solve></solve>
		</item>	 -->
	</questionList>
</note>