<note>
  <name>数据引擎产品版本发布说明书（V1.3.1）</name>
  <date>2019/04/03</date>
  <specialityList>
    <name>清单特性</name>
    <item>
      <Introduction>功能优化</Introduction>
      <content>UI界面优化展示</content>
      <sysName>数据工厂接入源类型优化</sysName>
      <remark></remark>
    </item>
    <item>
      <Introduction>功能优化</Introduction>
      <content>在单对象采集页面，选择一条运行的任务，进入详情页面，把当前状态运行改成暂停，弹出调用成功后，列表实时刷新任务状态</content>
      <sysName>数据接入汇聚</sysName>
      <remark></remark>
    </item>
    <item>
      <Introduction>功能优化</Introduction>
      <content>新建数据源时，IP地址格式校验</content>
      <sysName>数据接入汇聚</sysName>
      <remark></remark>
    </item>
    <item>
      <Introduction>功能优化</Introduction>
      <content>分别通过用户标记和单表采集入口进去，资源名称显示不一致</content>
      <sysName>数据接入汇聚</sysName>
      <remark></remark>
    </item>
  </specialityList>
  <changeList>
    <name>重大变更列表</name>
  </changeList>
  <finishedPunchList>
    <name>解决问题清单</name>
    <item>
      <Introduction>问题修复</Introduction>
      <content>修复：在任务中心查询“准备中”状态，会附带查询出状态为运行的记录</content>
      <sysName>任务中心</sysName>
      <remark></remark>
    </item>
    <item>
      <Introduction>问题修复</Introduction>
      <content>修复：设置任务 创建Impala表失败 源端表字段名包含Impala关键字</content>
      <sysName>接入汇聚</sysName>
      <remark></remark>
    </item>
  </finishedPunchList>
  <questionList>
    <name>已知问题和限制</name>
    <item>
      <Introduction>已知限制</Introduction>
      <content>对于结构化数据源接入，数据接入目前大小写敏感，对于同字段名在不同表有不同的大小写，数据工厂默认为不同的表结构（SJGC-455）</content>
      <sysName>数据接入</sysName>
      <remark></remark>
    </item>
    <item>
      <Introduction>已知限制</Introduction>
      <content>对于数据量大的表汇聚，剩余数据量和待处理数据量显示不准-这是预估值，仅供参考，不支持精准匹配（SJGC-421）</content>
      <sysName>数据汇聚</sysName>
      <remark></remark>
    </item>
  </questionList>
</note>
