<note>
	<name>数据资产版本发布说明20190425（V1.4.3）</name>
	<date>2019/04/25</date>
	<specialityList>
		<name>清单特性</name>
		<item>
			<Introduction>功能调整</Introduction>
			<content>统一页面中增删改查操作按钮位置，优化相应操作中的校验逻辑</content>
			<sysName>数据资产</sysName>
			<remark></remark>
		</item>
		<item>
			<Introduction>功能调整</Introduction>
			<content>调整专题管理，从table中提取专题类别树形结构，与标签管理等功能保持一致</content>
			<sysName>数据资产</sysName>
			<remark></remark>
		</item>
		<item>
			<Introduction>功能优化</Introduction>
			<content>优化统计图中title信息、刻度单位、图例提示信息等内容</content>
			<sysName>数据资产</sysName>
			<remark></remark>
		</item>
		<item>
			<Introduction>功能优化</Introduction>
			<content>优化资源中心元数据展示信息，添加字段名中文描述</content>
			<sysName>数据资产</sysName>
			<remark></remark>
		</item>
		<item>
			<Introduction>功能优化</Introduction>
			<content>优化配置管理字典数据排序规则</content>
			<sysName>数据资产</sysName>
			<remark></remark>
		</item>
		<item>
			<Introduction>新功能</Introduction>
			<content>资源中心添加默认查询全部搜索功能</content>
			<sysName>数据资产</sysName>
			<remark></remark>
		</item>
	</specialityList>
	<changeList>
		<name>重大变更列表</name>
	</changeList>
	<finishedPunchList>
		<name>解决问题清单</name>
	</finishedPunchList>
	<questionList>
		<name>已知问题和限制</name>
	</questionList>
</note>